{
  "run1": [
    "293", "276", "265", "259", "257", "256", "251",
    "248", "77", "275", "242", "240", "285", "260"
  ],
  "run2": [
    "293", "276", "265", "259", "257", "256", "251",
    "248", "77", "275", "242", "240", "285", "260"
  ],
  "run3": [
    "293", "276", "265", "259", "257", "256", "251",
    "248", "77", "275", "242", "240", "285", "260"
  ],
  "run4": [
    "293", "276", "265", "259", "257", "256", "251",
    "248", "77", "275", "242", "240", "285", "260"
  ],
  "run5": [
    "293", "276", "265", "259", "257", "256", "251",
    "248", "77", "275", "242", "240", "285", "260"
  ],
  "run6": [
    "293", "276", "265", "259", "257", "256", "251",
    "248", "77", "275", "242", "240", "285", "260"
  ]
}
