{
    "CV44 Original.pdf": {
        "interests": [
            "Startups",
            "Productivity"
        ]
    },
    "CV56 Original.pdf": {
        "interests": [
            "Startups",
            "business models"
        ]
    },
    "CV43 Original.pdf": {
        "interests": [
            "Digital branding",
            "Photography"
        ]
    },
    "CV11 Original.pdf": {
        "interests": [
            "Personal finance",
            "Pilates",
            "Budgeting"
        ]
    },
    "CV51 Original.pdf": {
        "interests": [
            "Talent development",
            "Wellbeing"
        ]
    },
    "CV75 Original.pdf": {
        "interests": [
            "International markets",
            "Travel"
        ]
    },
    "CV16 Original.pdf": {
        "interests": [
            "Entrepreneurship",
            "Public Policy",
            "Mentoring"
        ]
    },
    "CV20 Original.pdf": {
        "interests": [
            "Travel",
            "Economics podcasts"
        ]
    },
    "CV27 Original.pdf": {
        "interests": [
            "Geopolitics",
            "Languages"
        ]
    },
    "CV72 Original.pdf": {
        "interests": [
            "Analytics",
            "Automation"
        ]
    },
    "CV67 Original.pdf": {
        "interests": [
            "Banking",
            "learning"
        ]
    },
    "CV98 Original.pdf": {
        "interests": [
            "Humanitarian action"
        ]
    },
    "CV32 Original.pdf": {
        "interests": [
            "International trade",
            "Travel"
        ]
    },
    "CV60 Original.pdf": {
        "interests": []
    },
    "CV17 Original.pdf": {
        "interests": [
            "Data visualization",
            "Hiking"
        ]
    },
    "CV35 Original.pdf": {
        "interests": [
            "Social impact",
            "Project management"
        ]
    },
    "CV10 Original.pdf": {
        "interests": [
            "Travel",
            "Football",
            "Online Courses"
        ]
    },
    "CV50 Original.pdf": {
        "interests": [
            "Cross-border trade",
            "Travel"
        ]
    },
    "CV42 Original.pdf": {
        "interests": [
            "Data storytelling",
            "Jogging"
        ]
    },
    "CV45 Original.pdf": {
        "interests": [
            "Public policy",
            "analysis"
        ]
    },
    "CV57 Original.pdf": {
        "interests": [
            "Corporate finance",
            "self study"
        ]
    },
    "CV61 Original.pdf": {
        "interests": [
            "Corporate finance",
            "Analytics"
        ]
    },
    "CV34 Original.pdf": {
        "interests": [
            "Business strategy",
            "Hiking"
        ]
    },
    "CV33 Original.pdf": {
        "interests": [
            "Data visualization",
            "Running"
        ]
    },
    "CV73 Original.pdf": {
        "interests": [
            "Social media",
            "Communication"
        ]
    },
    "CV99 Original.pdf": {
        "interests": [
            "Organization",
            "Process efficiency"
        ]
    },
    "CV26 Original.pdf": {
        "interests": [
            "Startups",
            "Social impact"
        ]
    },
    "CV66 Original.pdf": {
        "interests": [
            "Entrepreneurship",
            "Innovation"
        ]
    },
    "CV74 Original.pdf": {
        "interests": [
            "Operations efficiency",
            "Fitness"
        ]
    },
    "CV81 Original.pdf": {
        "interests": [
            "Corporate finance",
            "Yoga"
        ]
    },
    "CV21 Original.pdf": {
        "interests": [
            "Women entrepreneurship",
            "Reading"
        ]
    },
    "CV79 Original.pdf": {
        "interests": [
            "Corporate finance",
            "Self development"
        ]
    },
    "CV86 Original.pdf": {
        "interests": [
            "Brand strategy",
            "Communication"
        ]
    },
    "CV7 Original.pdf": {
        "interests": [
            "Case competitions",
            "Sustainability strategy",
            "Pilates"
        ]
    },
    "CV39 Original.pdf": {
        "interests": [
            "Corporate finance",
            "Learning languages"
        ]
    },
    "CV93 Original.pdf": {
        "interests": [
            "Personal finance",
            "Continuous learning"
        ]
    },
    "CV94 Original.pdf": {
        "interests": [
            "Local business development"
        ]
    },
    "CV0 Original.pdf": {
        "interests": [
            "Football",
            "Macroeconomics",
            "Entrepreneurship",
            "Endurance Running"
        ]
    },
    "CV48 Original.pdf": {
        "interests": [
            "International markets",
            "News"
        ]
    },
    "CV87 Original.pdf": {
        "interests": [
            "Corporate finance",
            "Reporting"
        ]
    },
    "CV95 Original.pdf": {
        "interests": [
            "Social projects",
            "organization"
        ]
    },
    "CV92 Original.pdf": {
        "interests": [
            "International trade",
            "Travel"
        ]
    },
    "CV38 Original.pdf": {
        "interests": [
            "Operations efficiency",
            "Fitness"
        ]
    },
    "CV78 Original.pdf": {
        "interests": [
            "Tech products",
            "Automation"
        ]
    },
    "CV49 Original.pdf": {
        "interests": [
            "Corporate finance",
            "Self development"
        ]
    },
    "CV80 Original.pdf": {
        "interests": [
            "Retail strategy",
            "Running"
        ]
    },
    "CV1 Original.pdf": {
        "interests": [
            "Stock markets",
            "Yoga",
            "Public speaking",
            "Financial literacy initiatives"
        ]
    },
    "CV6 Original.pdf": {
        "interests": [
            "Data science competitions",
            "Cycling",
            "Technology trends"
        ]
    },
    "CV90 Original.pdf": {
        "interests": [
            "Process improvement",
            "Sports"
        ]
    },
    "CV97 Original.pdf": {
        "interests": [
            "International cooperation"
        ]
    },
    "CV68 Original.pdf": {
        "interests": [
            "Process efficiency",
            "Fitness"
        ]
    },
    "CV82 Original.pdf": {
        "interests": [
            "International trade",
            "Mentoring"
        ]
    },
    "CV28 Original.pdf": {
        "interests": [
            "Business strategy",
            "Fitness"
        ]
    },
    "CV85 Original.pdf": {
        "interests": [
            "Leadership",
            "Business Development"
        ]
    },
    "CV59 Original.pdf": {
        "interests": [
            "International cooperation",
            "Development"
        ]
    },
    "CV19 Original.pdf": {
        "interests": [
            "Professional growth",
            "finance books"
        ]
    },
    "CV3 Original.pdf": {
        "interests": [
            "Photography",
            "Fashion Marketing",
            "Content Creation"
        ]
    },
    "CV4 Original.pdf": {
        "interests": [
            "Martial arts",
            "Process optimization",
            "Productivity systems"
        ]
    },
    "CV83 Original.pdf": {
        "interests": []
    },
    "CV29 Original.pdf": {
        "interests": [
            "Corporate finance",
            "Sustainability"
        ]
    },
    "CV84 Original.pdf": {
        "interests": [
            "Data science",
            "Teaching"
        ]
    },
    "CV69 Original.pdf": {
        "interests": [
            "Data visualization",
            "Analytics"
        ]
    },
    "CV96 Original.pdf": {
        "interests": [
            "Scaling businesses",
            "Leadership"
        ]
    },
    "CV91 Original.pdf": {
        "interests": [
            "Branding",
            "Content creation"
        ]
    },
    "CV58 Original.pdf": {
        "interests": [
            "Operations excellence",
            "Cycling"
        ]
    },
    "CV2 Original.pdf": {
        "interests": [
            "Cycling",
            "geopolitics",
            "luxury industry trends"
        ]
    },
    "CV5 Original.pdf": {
        "interests": [
            "International relations",
            "Volunteering",
            "Travel"
        ]
    },
    "CV18 Original.pdf": {
        "interests": [
            "Economic development",
            "Public speaking"
        ]
    },
    "CV47 Original.pdf": {
        "interests": [
            "Process optimization",
            "Yoga"
        ]
    },
    "CV12 Original.pdf": {
        "interests": [
            "Content creation",
            "Social media",
            "Photography"
        ]
    },
    "CV40 Original.pdf": {
        "interests": [
            "Hospitality trends",
            "Travel"
        ]
    },
    "CV15 Original.pdf": {
        "interests": [
            "Psychology",
            "Volunteering",
            "Reading"
        ]
    },
    "CV8 Original.pdf": {
        "interests": [
            "Entrepreneurship",
            "Podcasts",
            "Fintech Innovation"
        ]
    },
    "CV52 Original.pdf": {
        "interests": [
            "Financial markets",
            "Fitness"
        ]
    },
    "CV55 Original.pdf": {
        "interests": [
            "Data modeling",
            "Analytics"
        ]
    },
    "CV64 Original.pdf": {
        "interests": [
            "Case interviews",
            "Geopolitics"
        ]
    },
    "CV31 Original.pdf": {
        "interests": [
            "Content creation",
            "Branding"
        ]
    },
    "CV89 Original.pdf": {
        "interests": [
            "Operations optimization",
            "Fitness"
        ]
    },
    "CV63 Original.pdf": {
        "interests": [
            "Event marketing",
            "Communication"
        ]
    },
    "CV36 Original.pdf": {
        "interests": [
            "Startups",
            "Networking"
        ]
    },
    "CV76 Original.pdf": {
        "interests": [
            "Entrepreneurship",
            "Learning"
        ]
    },
    "CV23 Original.pdf": {
        "interests": [
            "Case competitions",
            "Debating"
        ]
    },
    "CV71 Original.pdf": {
        "interests": [
            "Economic policy",
            "Sustainability"
        ]
    },
    "CV24 Original.pdf": {
        "interests": [
            "Process improvement",
            "sports"
        ]
    },
    "CV53 Original.pdf": {
        "interests": [
            "Brand storytelling",
            "Design"
        ]
    },
    "CV54 Original.pdf": {
        "interests": [
            "Manufacturing systems",
            "Learning"
        ]
    },
    "CV9 Original.pdf": {
        "interests": [
            "Professional development",
            "Public speaking",
            "Mentoring"
        ]
    },
    "CV14 Original.pdf": {
        "interests": [
            "Running",
            "process optimization",
            "podcasts"
        ]
    },
    "CV41 Original.pdf": {
        "interests": [
            "Financial inclusion",
            "Reading"
        ]
    },
    "CV70 Original.pdf": {
        "interests": [
            "Business development",
            "Networking"
        ]
    },
    "CV13 Original.pdf": {
        "interests": [
            "Startups",
            "Networking events",
            "Yoga"
        ]
    },
    "CV25 Original.pdf": {
        "interests": [
            "Photography",
            "Travel branding"
        ]
    },
    "CV46 Original.pdf": {
        "interests": [
            "Entrepreneurship",
            "Learning"
        ]
    },
    "CV88 Original.pdf": {
        "interests": [
            "Global markets",
            "travel"
        ]
    },
    "CV22 Original.pdf": {
        "interests": [
            "Data projects",
            "Automation"
        ]
    },
    "CV62 Original.pdf": {
        "interests": []
    },
    "CV30 Original.pdf": {
        "interests": [
            "Personal finance",
            "Cycling"
        ]
    },
    "CV77 Original.pdf": {
        "interests": [
            "Energy markets",
            "Strategy"
        ]
    },
    "CV37 Original.pdf": {
        "interests": [
            "Sustainability",
            "Yoga"
        ]
    },
    "CV65 Original.pdf": {
        "interests": [
            "International cooperation",
            "Volunteering"
        ]
    }
}